hashtagger/__init__.py
hashtagger/hashtagger.py
hashtagger-0.2.1.dist-info/LICENSE.txt
hashtagger-0.2.1.dist-info/METADATA
hashtagger-0.2.1.dist-info/WHEEL
hashtagger-0.2.1.dist-info/top_level.txt
hashtagger-0.2.1.dist-info/RECORD
