Metadata-Version: 2.1
Name: hashtagger
Version: 0.2.1
Summary: A hashtag generator using TensorFlow and NLTK
Home-page: 
Author: Meet Jethwa
Author-email: meetjethwa3@gmail.com
License: MIT
Keywords: tagger tensorflow nltk
Classifier: Development Status :: 5 - Production/Stable
Classifier: Intended Audience :: Education
Classifier: Operating System :: OS Independent
Classifier: License :: OSI Approved :: MIT License
Classifier: Programming Language :: Python
Classifier: Programming Language :: Python :: 3
Classifier: Programming Language :: Python :: 3.7
Classifier: Programming Language :: Python :: 3.8
Classifier: Programming Language :: Python :: 3.9
Classifier: Programming Language :: Python :: 3.10
Classifier: Programming Language :: Python :: 3.11
License-File: LICENSE.txt
Requires-Dist: opencv-python
Requires-Dist: numpy
Requires-Dist: tensorflow
Requires-Dist: nltk
